verilog_codes/combinational_logic/examples/example1.v
module example1(input a, b, c, d,
                output y);

    assign y = (a & ~b & ~c & ~d) | (d & (~a | b | c));

endmodule

verilog_codes/combinational_logic/examples/example1_tb.v
module example1_tb();

reg ia, ib, ic, id;
wire o;
integer n;

example1 dut(.a(ia), .b(ib), .c(ic), .d(id), .y(o));

initial begin
  $dumpfile("example1.vcd");
  $dumpvars();

  $display("\nA B C D | Y");  
  $monitor("%b %b %b %b | %b", ia, ib, ic, id, o);

  for(n=0;n<16;n=n+1) begin
    {ia,ib,ic,id} = n;
    #10;
  end

end

endmodule

verilog_codes/combinational_logic/examples/example1.vcd
$date
	Tue Apr 11 21:18:35 2023
$end
$version
	Icarus Verilog
$end
$timescale
	1s
$end
$scope module example1_tb $end
$var wire 1 ! o $end
$var reg 1 " ia $end
$var reg 1 # ib $end
$var reg 1 $ ic $end
$var reg 1 % id $end
$var integer 32 & n [31:0] $end
$scope module dut $end
$var wire 1 " a $end
$var wire 1 # b $end
$var wire 1 $ c $end
$var wire 1 % d $end
$var wire 1 ! y $end
$upscope $end
$upscope $end
$enddefinitions $end
$comment Show the parameter values. $end
$dumpall
$end
#0
$dumpvars
b0 &
0%
0$
0#
0"
0!
$end
#10
1!
1%
b1 &
#20
0!
1$
0%
b10 &
#30
1!
1%
b11 &
#40
0!
1#
0$
0%
b100 &
#50
1!
1%
b101 &
#60
0!
1$
0%
b110 &
#70
1!
1%
b111 &
#80
1!
1"
0#
0$
0%
b1000 &
#90
0!
1%
b1001 &
#100
0!
1$
0%
b1010 &
#110
1!
1%
b1011 &
#120
0!
1#
0$
0%
b1100 &
#130
1!
1%
b1101 &
#140
0!
1$
0%
b1110 &
#150
1!
1%
b1111 &
#160
b10000 &
