verilog_codes/combinational_logic/examples/example0.v
module example0(input a, b, c,
                output y);

  assign y = (~b&~c)|(a&~b);

endmodule

verilog_codes/combinational_logic/examples/example0_tb.v
module example0_tb();

  reg ia, ib, ic;
  wire o;
  integer n;

  example0 dut(.a(ia), .b(ib), .c(ic), .y(o));

  initial begin
    $dumpfile("example0.vcd");
    $dumpvars();

    $display("a b c | y");
    $monitor("%b %b %b | %b", ia, ib, ic, o);

    for(n=0;n<8;n=n+1) begin
      {ia, ib, ic} = n;
      #10;
    end

  end

endmodule

verilog_codes/combinational_logic/examples/example0.vcd
$date
	Fri Apr 14 12:29:17 2023
$end
$version
	Icarus Verilog
$end
$timescale
	1s
$end
$scope module example0_tb $end
$var wire 1 ! o $end
$var reg 1 " ia $end
$var reg 1 # ib $end
$var reg 1 $ ic $end
$var integer 32 % n [31:0] $end
$scope module dut $end
$var wire 1 " a $end
$var wire 1 # b $end
$var wire 1 $ c $end
$var wire 1 ! y $end
$upscope $end
$upscope $end
$enddefinitions $end
$comment Show the parameter values. $end
$dumpall
$end
#0
$dumpvars
b0 %
0$
0#
0"
1!
$end
#10
0!
1$
b1 %
#20
1#
0$
b10 %
#30
1$
b11 %
#40
1!
1"
0#
0$
b100 %
#50
1$
b101 %
#60
0!
1#
0$
b110 %
#70
1$
b111 %
#80
b1000 %
