verilog_codes/mux21.v
module mux21(d0, d1, s, y);

    input d0, d1;
    input s;
    output y;

    assign y = (~s & d0)|(s & d1);

endmodule

verilog_codes/mux/mux21_tb.v
module mux21_tb();

    reg d0, d1, s;
    wire y;
    integer i;

    mux21 dut(d0, d1, s, y);

    initial begin
      $dumpfile("mux21.vcd");
      $dumpvars();


      for(i=0;i<8;i=i+1) begin
        {s,d1,d0} = i; 
        #10;
        $display("s = %b d1 = %b d0 = %b | y = %b", s, d1, d0, y);
      end
    
    end

endmodule

verilog_codes/combinational_logic/mux/mux21.vcd
$date
	Wed Mar 15 15:13:53 2023
$end
$version
	Icarus Verilog
$end
$timescale
	1s
$end
$scope module mux21_tb $end
$var wire 1 ! y $end
$var reg 1 " d0 $end
$var reg 1 # d1 $end
$var reg 1 $ s $end
$var integer 32 % i [31:0] $end
$scope module dut $end
$var wire 1 " d0 $end
$var wire 1 # d1 $end
$var wire 1 $ s $end
$var wire 1 ! y $end
$upscope $end
$upscope $end
$enddefinitions $end
$comment Show the parameter values. $end
$dumpall
$end
#0
$dumpvars
b0 %
0$
0#
0"
0!
$end
#10
1!
1"
b1 %
#20
0!
1#
0"
b10 %
#30
1!
1"
b11 %
#40
0!
1$
0#
0"
b100 %
#50
1"
b101 %
#60
1!
1#
0"
b110 %
#70
1"
b111 %
#80
b1000 %
