verilog_codes/combinational_logic/priority_tb.v
module priority_tb();

  reg i0, i1, i2, i3;
  wire o0, o1, o2, o3;
  integer n;

  priority dut(.d0(i0), .d1(i1), .d2(i2), .d3(i3), .y0(o0), .y1(o1), .y2(o2), .y3(o3));

  initial begin
    $dumpfile("priority.vcd");
    $dumpvars();

    $display("d3 d2 d1 d0 | y3 y2 y1 y0");
    $monitor("%b  %b  %b  %b  | %b  %b  %b  %b", i3 , i3, i1, i0, o3, o2, o1, o0);

    for(n=0;n<16;n=n+1) begin
        {i3, i2, i1, i0} = n;
        #10;
    end
  
  end

endmodule

verilog_codes/combinational_logic/priority.vcd
$date
	Thu Mar 23 18:02:59 2023
$end
$version
	Icarus Verilog
$end
$timescale
	1s
$end
$scope module priority_tb $end
$var wire 1 ! o3 $end
$var wire 1 " o2 $end
$var wire 1 # o1 $end
$var wire 1 $ o0 $end
$var reg 1 % i0 $end
$var reg 1 & i1 $end
$var reg 1 ' i2 $end
$var reg 1 ( i3 $end
$var integer 32 ) n [31:0] $end
$scope module dut $end
$var wire 1 % d0 $end
$var wire 1 & d1 $end
$var wire 1 ' d2 $end
$var wire 1 ( d3 $end
$var wire 1 $ y0 $end
$var wire 1 # y1 $end
$var wire 1 " y2 $end
$var wire 1 ! y3 $end
$upscope $end
$upscope $end
$enddefinitions $end
$comment Show the parameter values. $end
$dumpall
$end
#0
$dumpvars
b0 )
0(
0'
0&
0%
0$
0#
0"
0!
$end
#10
1$
1%
b1 )
#20
1#
0$
1&
0%
b10 )
#30
1%
b11 )
#40
1"
0#
1'
0&
0%
b100 )
#50
1%
b101 )
#60
1&
0%
b110 )
#70
1%
b111 )
#80
0"
1!
1(
0'
0&
0%
b1000 )
#90
1%
b1001 )
#100
1&
0%
b1010 )
#110
1%
b1011 )
#120
1'
0&
0%
b1100 )
#130
1%
b1101 )
#140
1&
0%
b1110 )
#150
1%
b1111 )
#160
b10000 )
