verilog_codes/ternarymux21.v
module ternarymux21(input d0, d1,
                    input s,
                    output y);

    assign y = s ? d1 : d0;

endmodule

verilog_codes/structuralmux41.v
module structuralmux41(input d0, d1, d2, d3,
                       input [1:0] s,
                       output y);

    wire low, high;

    ternarymux21 lowmux(.d0(d0), .d1(d1), .s(s[0]), .y(low));
    ternarymux21 highmux(.d0(d2), .d1(d3), .s(s[0]), .y(high));
    ternarymux21 finalmux(.d0(low), .d1(high), .s(s[1]), .y(y));

endmodule

verilog_codes/combinational_logic/mux/structuralmux41_tb.v
`timescale 1ns/1ns

module structuralmux41_tb();

  reg i0, i1, i2, i3;
  reg [1:0] s;
  wire o;
  integer n;

  structuralmux41 dut(.d0(i0), .d1(i1), .d2(i2), .d3(i3), .s(s), .y(o));

  initial begin
    $dumpfile("structuralmux41.vcd");
    $dumpvars();

    $monitor("%b %b %b %b %b %b | %b", s[1], s[0], i3, i2, i1, i0, o);

    for(n=0;n<64;n=n+1) begin
      {s[1], s[0], i3, i2, i1, i0}=n;
      #10;
    end
  
  end

endmodule

verilog_codes/structuralmux41.vcd
$date
	Fri Mar 17 20:14:18 2023
$end
$version
	Icarus Verilog
$end
$timescale
	1ns
$end
$scope module structuralmux41_tb $end
$var wire 1 ! o $end
$var reg 1 " i0 $end
$var reg 1 # i1 $end
$var reg 1 $ i2 $end
$var reg 1 % i3 $end
$var reg 2 & s [1:0] $end
$var integer 32 ' n [31:0] $end
$scope module dut $end
$var wire 1 " d0 $end
$var wire 1 # d1 $end
$var wire 1 $ d2 $end
$var wire 1 % d3 $end
$var wire 2 ( s [1:0] $end
$var wire 1 ! y $end
$var wire 1 ) low $end
$var wire 1 * high $end
$scope module finalmux $end
$var wire 1 + s $end
$var wire 1 ! y $end
$var wire 1 * d1 $end
$var wire 1 ) d0 $end
$upscope $end
$scope module highmux $end
$var wire 1 $ d0 $end
$var wire 1 % d1 $end
$var wire 1 , s $end
$var wire 1 * y $end
$upscope $end
$scope module lowmux $end
$var wire 1 " d0 $end
$var wire 1 # d1 $end
$var wire 1 - s $end
$var wire 1 ) y $end
$upscope $end
$upscope $end
$upscope $end
$enddefinitions $end
$comment Show the parameter values. $end
$dumpall
$end
#0
$dumpvars
0-
0,
0+
0*
0)
b0 (
b0 '
b0 &
0%
0$
0#
0"
0!
$end
#10
1!
1)
1"
b1 '
#20
0!
0)
1#
0"
b10 '
#30
1!
1)
1"
b11 '
#40
0!
1*
0)
1$
0#
0"
b100 '
#50
1!
1)
1"
b101 '
#60
0!
0)
1#
0"
b110 '
#70
1!
1)
1"
b111 '
#80
0!
0*
0)
1%
0$
0#
0"
b1000 '
#90
1!
1)
1"
b1001 '
#100
0!
0)
1#
0"
b1010 '
#110
1!
1)
1"
b1011 '
#120
0!
1*
0)
1$
0#
0"
b1100 '
#130
1!
1)
1"
b1101 '
#140
0!
0)
1#
0"
b1110 '
#150
1!
1)
1"
b1111 '
#160
0!
1-
1,
0*
0)
b1 &
b1 (
0%
0$
0#
0"
b10000 '
#170
1"
b10001 '
#180
1!
1)
1#
0"
b10010 '
#190
1"
b10011 '
#200
0!
0)
1$
0#
0"
b10100 '
#210
1"
b10101 '
#220
1!
1)
1#
0"
b10110 '
#230
1"
b10111 '
#240
0!
1*
0)
1%
0$
0#
0"
b11000 '
#250
1"
b11001 '
#260
1!
1)
1#
0"
b11010 '
#270
1"
b11011 '
#280
0!
0)
1$
0#
0"
b11100 '
#290
1"
b11101 '
#300
1!
1)
1#
0"
b11110 '
#310
1"
b11111 '
#320
0!
1+
0-
0,
0*
0)
b10 &
b10 (
0%
0$
0#
0"
b100000 '
#330
1)
1"
b100001 '
#340
0)
1#
0"
b100010 '
#350
1)
1"
b100011 '
#360
1!
1*
0)
1$
0#
0"
b100100 '
#370
1)
1"
b100101 '
#380
0)
1#
0"
b100110 '
#390
1)
1"
b100111 '
#400
0!
0*
0)
1%
0$
0#
0"
b101000 '
#410
1)
1"
b101001 '
#420
0)
1#
0"
b101010 '
#430
1)
1"
b101011 '
#440
1!
1*
0)
1$
0#
0"
b101100 '
#450
1)
1"
b101101 '
#460
0)
1#
0"
b101110 '
#470
1)
1"
b101111 '
#480
0!
1-
1,
0*
0)
b11 &
b11 (
0%
0$
0#
0"
b110000 '
#490
1"
b110001 '
#500
1)
1#
0"
b110010 '
#510
1"
b110011 '
#520
0)
1$
0#
0"
b110100 '
#530
1"
b110101 '
#540
1)
1#
0"
b110110 '
#550
1"
b110111 '
#560
1!
1*
0)
1%
0$
0#
0"
b111000 '
#570
1"
b111001 '
#580
1)
1#
0"
b111010 '
#590
1"
b111011 '
#600
0)
1$
0#
0"
b111100 '
#610
1"
b111101 '
#620
1)
1#
0"
b111110 '
#630
1"
b111111 '
#640
b1000000 '
