verilog_codes/ternarymux21.v
module ternarymux21(input d0, d1,
                    input s,
                    output y);

    assign y = s ? d1 : d0;

endmodule

verilog_codes/mux/ternarymux21_tb.v
module ternarymux21_tb();

  reg i0, i1;
  reg s;
  wire o;
  integer n;

  ternarymux21 dut(.d0(i0), .d1(i1), .s(s), .y(o));

  initial begin
    $dumpfile("ternarymux21.vcd");
    $dumpvars();

    $monitor("%b %b %b | %b", s, i1, i0, o);

    for(n=0;n<8;n=n+1) begin
      {s, i1, i0} = n;
      #10;
    end
  
  end

endmodule

verilog_codes/ternarymux21.vcd
$date
	Fri Mar 17 19:53:37 2023
$end
$version
	Icarus Verilog
$end
$timescale
	1s
$end
$scope module ternarymux21_tb $end
$var wire 1 ! o $end
$var reg 1 " i0 $end
$var reg 1 # i1 $end
$var reg 1 $ s $end
$var integer 32 % n [31:0] $end
$scope module dut $end
$var wire 1 " d0 $end
$var wire 1 # d1 $end
$var wire 1 $ s $end
$var wire 1 ! y $end
$upscope $end
$upscope $end
$enddefinitions $end
$comment Show the parameter values. $end
$dumpall
$end
#0
$dumpvars
b0 %
0$
0#
0"
0!
$end
#10
1!
1"
b1 %
#20
0!
1#
0"
b10 %
#30
1!
1"
b11 %
#40
0!
1$
0#
0"
b100 %
#50
1"
b101 %
#60
1!
1#
0"
b110 %
#70
1"
b111 %
#80
b1000 %
