verilog_codes/ternarymux41.v
module ternarymux41(input [3:0] a,
                    input [1:0] s,
                    output y);

    assign y = s[1] ? (s[0] ? a[3] : a[2]) : (s[0] ? a[1] : a[0]);

endmodule

verilog_codes/ternarymux41_tb.v
module ternarymux41_tb();

  reg [3:0] i;
  reg [1:0] s;
  wire o;
  integer n;

  ternarymux41 dut(.a(i), .s(s), .y(o));

  initial begin
    $dumpfile("ternarymux41.vcd");
    $dumpvars();

    $display("s1 s0 a3 a2 a1 a0 | y");
    $monitor("%b  %b  %b  %b  %b  %b  | %b", s[1], s[0], i[3], i[2], i[1], i[0], o);

    for(n=0;n<64;n=n+1) begin
      {s[1], s[0], i[3], i[2], i[1], i[0]} = n;
      #1;
    end
  
  end

endmodule

verilog_codes/ternarymux41.vcd
$date
	Fri Mar 17 08:40:43 2023
$end
$version
	Icarus Verilog
$end
$timescale
	1s
$end
$scope module ternarymux41_tb $end
$var wire 1 ! o $end
$var reg 4 " i [3:0] $end
$var reg 2 # s [1:0] $end
$var integer 32 $ n [31:0] $end
$scope module dut $end
$var wire 4 % a [3:0] $end
$var wire 2 & s [1:0] $end
$var wire 1 ! y $end
$upscope $end
$upscope $end
$enddefinitions $end
$comment Show the parameter values. $end
$dumpall
$end
#0
$dumpvars
b0 &
b0 %
b0 $
b0 #
b0 "
0!
$end
#1
1!
b1 "
b1 %
b1 $
#2
0!
b10 "
b10 %
b10 $
#3
1!
b11 "
b11 %
b11 $
#4
0!
b100 "
b100 %
b100 $
#5
1!
b101 "
b101 %
b101 $
#6
0!
b110 "
b110 %
b110 $
#7
1!
b111 "
b111 %
b111 $
#8
0!
b1000 "
b1000 %
b1000 $
#9
1!
b1001 "
b1001 %
b1001 $
#10
0!
b1010 "
b1010 %
b1010 $
#11
1!
b1011 "
b1011 %
b1011 $
#12
0!
b1100 "
b1100 %
b1100 $
#13
1!
b1101 "
b1101 %
b1101 $
#14
0!
b1110 "
b1110 %
b1110 $
#15
1!
b1111 "
b1111 %
b1111 $
#16
0!
b1 #
b1 &
b0 "
b0 %
b10000 $
#17
b1 "
b1 %
b10001 $
#18
1!
b10 "
b10 %
b10010 $
#19
b11 "
b11 %
b10011 $
#20
0!
b100 "
b100 %
b10100 $
#21
b101 "
b101 %
b10101 $
#22
1!
b110 "
b110 %
b10110 $
#23
b111 "
b111 %
b10111 $
#24
0!
b1000 "
b1000 %
b11000 $
#25
b1001 "
b1001 %
b11001 $
#26
1!
b1010 "
b1010 %
b11010 $
#27
b1011 "
b1011 %
b11011 $
#28
0!
b1100 "
b1100 %
b11100 $
#29
b1101 "
b1101 %
b11101 $
#30
1!
b1110 "
b1110 %
b11110 $
#31
b1111 "
b1111 %
b11111 $
#32
0!
b10 #
b10 &
b0 "
b0 %
b100000 $
#33
b1 "
b1 %
b100001 $
#34
b10 "
b10 %
b100010 $
#35
b11 "
b11 %
b100011 $
#36
1!
b100 "
b100 %
b100100 $
#37
b101 "
b101 %
b100101 $
#38
b110 "
b110 %
b100110 $
#39
b111 "
b111 %
b100111 $
#40
0!
b1000 "
b1000 %
b101000 $
#41
b1001 "
b1001 %
b101001 $
#42
b1010 "
b1010 %
b101010 $
#43
b1011 "
b1011 %
b101011 $
#44
1!
b1100 "
b1100 %
b101100 $
#45
b1101 "
b1101 %
b101101 $
#46
b1110 "
b1110 %
b101110 $
#47
b1111 "
b1111 %
b101111 $
#48
0!
b11 #
b11 &
b0 "
b0 %
b110000 $
#49
b1 "
b1 %
b110001 $
#50
b10 "
b10 %
b110010 $
#51
b11 "
b11 %
b110011 $
#52
b100 "
b100 %
b110100 $
#53
b101 "
b101 %
b110101 $
#54
b110 "
b110 %
b110110 $
#55
b111 "
b111 %
b110111 $
#56
1!
b1000 "
b1000 %
b111000 $
#57
b1001 "
b1001 %
b111001 $
#58
b1010 "
b1010 %
b111010 $
#59
b1011 "
b1011 %
b111011 $
#60
b1100 "
b1100 %
b111100 $
#61
b1101 "
b1101 %
b111101 $
#62
b1110 "
b1110 %
b111110 $
#63
b1111 "
b1111 %
b111111 $
#64
b1000000 $
