verilog_codes/gates/andgate.v
module andgate(input [2:0] a,
           output y);

    assign y = &a;

endmodule

verilog_codes/gates/andgate_tb.v
module andgate_tb();

  reg [2:0] i;
  wire o;
  integer n;

  andgate dut(i, o);

  initial begin
    $dumpfile("andgate.vcd");
    $dumpvars();

    $display("a2 a1 a0 | y");
    $monitor("%b  %b  %b  | %b", i[2], i[1], i[0], o);

    for(n=0;n<8;n=n+1) begin
        {i[2], i[1], i[0]} = n;
        #10;
    end

  end

endmodule

verilog_codes/combinational_logic/gates/andgate.vcd
$date
	Fri Apr 14 12:13:14 2023
$end
$version
	Icarus Verilog
$end
$timescale
	1s
$end
$scope module andgate_tb $end
$var wire 1 ! o $end
$var reg 3 " i [2:0] $end
$var integer 32 # n [31:0] $end
$scope module dut $end
$var wire 3 $ a [2:0] $end
$var wire 1 ! y $end
$upscope $end
$upscope $end
$enddefinitions $end
$comment Show the parameter values. $end
$dumpall
$end
#0
$dumpvars
b0 $
b0 #
b0 "
0!
$end
#10
b1 "
b1 $
b1 #
#20
b10 "
b10 $
b10 #
#30
b11 "
b11 $
b11 #
#40
b100 "
b100 $
b100 #
#50
b101 "
b101 $
b101 #
#60
b110 "
b110 $
b110 #
#70
1!
b111 "
b111 $
b111 #
#80
b1000 #
