verilog_codes/combinational_logic/gates/orgate.v
module orgate(input [3:0] a,
              output y);

    assign y = |a;

endmodule

verilog_codes/orgate_tb.v
module orgate_tb();

  reg [3:0] i;
  wire o;
  integer n;

  orgate dut(.a(i), .y(o));

  initial begin
    $dumpfile("orgate.vcd");
    $dumpvars();

    $monitor("%b %b %b %b | %b", i[3], i[2], i[1], i[0], o);

    for(n=0;n<16;n=n+1) begin
      {i[3], i[2], i[1], i[0]} = n;
      #10;
    end
  
  end

endmodule

verilog_codes/combinational_logic/gates/orgate.vcd
$date
	Mon Mar 20 18:30:52 2023
$end
$version
	Icarus Verilog
$end
$timescale
	1s
$end
$scope module orgate_tb $end
$var wire 1 ! o $end
$var reg 4 " i [3:0] $end
$var integer 32 # n [31:0] $end
$scope module dut $end
$var wire 4 $ a [3:0] $end
$var wire 1 ! y $end
$upscope $end
$upscope $end
$enddefinitions $end
$comment Show the parameter values. $end
$dumpall
$end
#0
$dumpvars
b0 $
b0 #
b0 "
0!
$end
#10
1!
b1 "
b1 $
b1 #
#20
1!
b10 "
b10 $
b10 #
#30
b11 "
b11 $
b11 #
#40
1!
b100 "
b100 $
b100 #
#50
b101 "
b101 $
b101 #
#60
b110 "
b110 $
b110 #
#70
b111 "
b111 $
b111 #
#80
1!
b1000 "
b1000 $
b1000 #
#90
b1001 "
b1001 $
b1001 #
#100
b1010 "
b1010 $
b1010 #
#110
b1011 "
b1011 $
b1011 #
#120
b1100 "
b1100 $
b1100 #
#130
b1101 "
b1101 $
b1101 #
#140
b1110 "
b1110 $
b1110 #
#150
b1111 "
b1111 $
b1111 #
#160
b10000 #
